Week-1/alu.v
module alu(input[3:0]a,input[3:0]b,input[2:0]sel, output reg[3:0] out);

always@(*) begin
	case(sel[1:0])
	    3'b000:out=0;
            3'b001:out=a+b;
            3'b010:out=a-b;
            3'b011:out=a&b;
            3'b100:out=a|b;
            3'b101:out=~a;
            3'b110:out=~b;	
            3'b111:out=0;
            default:out=0;
        endcase
end

endmodule

Week-1/alu_tb.v
module alu_tb;

reg[3:0]a;
reg[3:0]b;
reg[2:0]sel;
wire[3:0]c;

alu i1(.a(a),.b(b),.sel(sel),.out(c));

initial begin
$dumpfile("test_alu.vcd");
$dumpvars(0,alu_tb);

#1 a=4'b0010;
#2 b=4'b0001;
#4 sel=3'b000;
#5 sel=3'b001;
#10 sel=3'b010;
#15 sel=3'b011;
#20 sel=3'b100;
#25 sel=3'b101;
#30 sel=3'b110;
#35 sel=3'b111;


#50 $finish;

end

endmodule

Week-1/test_alu.vcd
$date
	Mon May 20 18:54:32 2024
$end
$version
	Icarus Verilog
$end
$timescale
	1s
$end
$scope module alu_tb $end
$var wire 4 ! c [3:0] $end
$var reg 4 " a [3:0] $end
$var reg 4 # b [3:0] $end
$var reg 3 $ sel [2:0] $end
$scope module i1 $end
$var wire 4 % a [3:0] $end
$var wire 4 & b [3:0] $end
$var wire 3 ' sel [2:0] $end
$var reg 4 ( out [3:0] $end
$upscope $end
$upscope $end
$enddefinitions $end
#0
$dumpvars
bx (
bx '
bx &
bx %
bx $
bx #
bx "
bx !
$end
#1
b0 !
b0 (
b10 "
b10 %
#3
b1 #
b1 &
#7
b0 $
b0 '
#12
b11 !
b11 (
b1 $
b1 '
#22
b1 !
b1 (
b10 $
b10 '
#37
b0 !
b0 (
b11 $
b11 '
#57
b100 $
b100 '
#82
b11 !
b11 (
b101 $
b101 '
#112
b1 !
b1 (
b110 $
b110 '
#147
b0 !
b0 (
b111 $
b111 '
